{
  "sections": {
    "main-faq": {
      "type": "main-faq",
      "blocks": {
        "8f4acfdf-e277-4906-9849-918d43148b2a": {
          "type": "category_1",
          "settings": {
            "question": "Quels sont les tarifs et délais de livraison ?",
            "answer": "<p>Les délais de livraison indiqués sont en <strong>jours ouvrés<\/strong> (hors weekends et jours fériés).<\/p>",
            "image": "shopify:\/\/shop_images\/Capture_d_ecran_2023-04-26_a_15.07.30.png"
          }
        },
        "e534d746-64ae-4407-9460-81be9cc69904": {
          "type": "category_1",
          "settings": {
            "question": "Comment suivre mon colis ?",
            "answer": "<p>Lorsque votre colis sera expédié et pris en charge par le transporteur, <strong>vous recevrez un mail contenant un lien de suivi pour savoir où est votre commande<\/strong>. Vous pouvez aussi suivre votre commande à tout moment en <strong>cliquant ici<\/strong>.<\/p>"
          }
        },
        "8474b469-f201-4a4f-afff-6df338d8a35e": {
          "type": "category_1",
          "settings": {
            "question": "J'ai un souci de livraison, que faire ?",
            "answer": "<p>Vous pouvez joindre Adélaïde de notre équipe en écrivant à <a href=\"mailto:hello@we-pop-it.co\" title=\"mailto:hello@we-pop-it.co\"><strong>hello@we-pop-it.co<\/strong><\/a>, sur le chat du site ou via notre <strong>formulaire de contact<\/strong>.<\/p>"
          }
        },
        "25172bc4-ca1f-451f-bca2-ac945fa6ecb2": {
          "type": "category_1",
          "settings": {
            "question": "Mon colis a été indiqué comme livré, mais je n'ai rien dans ma boîte aux lettres. Est-ce normal ?",
            "answer": "<p>Il se peut que <strong>l’un de vos voisins ou que votre concierge l’ait récupéré pour vous<\/strong>, n’hésitez pas à vous renseigner auprès d’eux ! <\/p><p>Si ce n'est pas le cas, il arrive également que les transporteurs <strong>mettent à jour les statuts de livraison avant même d'avoir livré le colis<\/strong>. Nous vous invitons à attendre au moins 24 heures supplémentaires ouvrées ! <\/p><p>Si vous ne le recevez toujours pas, n'hésitez pas à nous envoyer un mail à <a href=\"mailto:hello@we-pop-it.co\" title=\"mailto:hello@we-pop-it.co\"><strong>hello@we-pop-it.co<\/strong><\/a> les jours suivants et nous trouverons une solution ensemble !<\/p>"
          }
        },
        "3714bd05-89fb-48f4-967a-db43635b8981": {
          "type": "category_1",
          "settings": {
            "question": "Mon colis est en retour à l'expéditeur, que va-t-il se passer ?",
            "answer": "<p>Si l'adresse que vous avez renseignée est incomplète ou que le <strong>colis a été endommagé<\/strong> pendant le transport, il arrive que <strong>le colis nous soit automatiquement renvoyé<\/strong>. <\/p><p>Dans ce cas, nous vous invitons à nous contacter à <a href=\"mailto:hello@we-pop-it.co\" title=\"mailto:hello@we-pop-it.co\"><strong>hello@we-pop-it.co<\/strong><\/a>, en nous renvoyant votre adresse complète si nécessaire, afin que nous puissions vous envoyer un <strong>nouveau colis au plus vite<\/strong>.<\/p>"
          }
        },
        "ebe4ec3f-1534-4538-a707-239aba6a2d8b": {
          "type": "category_1",
          "settings": {
            "question": "Vais-je devoir payer des frais de douane pour une livraison à l'étranger ?",
            "answer": "<p>Les frais de douane sont <strong>spécifiques à chaque pays<\/strong> et dépendent du montant de votre commande. Lorsque des frais s'appliquent, <strong>ils sont à votre charge.<\/strong><\/p>"
          }
        },
        "65687ccb-ea2b-4465-8ec4-b88b11b7c933": {
          "type": "category_1",
          "settings": {
            "question": "Quelle est votre politique de retour ou d'échange ?",
            "answer": "<p>Nous acceptons les retours pour les <strong>produits neufs et non utilisés dans un délai de 30 jours<\/strong> après la réception de la commande. Les produits doivent être dans leur <strong>emballage d'origine, en parfait état<\/strong>. Les frais de retour sont à votre charge. Nous vous invitons à nous contacter à <a href=\"mailto:hello@we-pop-it.co\" title=\"mailto:hello@we-pop-it.co\"><strong>hello@we-pop-it.co<\/strong><\/a><strong> <\/strong>pour que nous puissions traiter votre retour dans les plus brefs délais. Pour effectuer un <strong>échange, vous pouvez suivre la procédure de retour classique<\/strong> puis passer une nouvelle commande.<\/p>"
          }
        },
        "1b714378-dfb3-41a0-9f69-6680410b2b28": {
          "type": "category_2",
          "settings": {
            "question": "Est-ce que je peux modifier les informations de ma commande (produits, adresse, ...) ?",
            "answer": "<p>Une fois la commande passée, il n'est malheureusement <strong>pas possible de la modifier<\/strong>.<\/p>"
          }
        },
        "2174bf0a-c056-43eb-b32f-1fa32235d0ac": {
          "type": "category_2",
          "settings": {
            "question": "Est-ce que je peux annuler ma commande ?",
            "answer": "<p>Avec un peu de chance, votre <strong>commande n'a pas encore été traitée<\/strong> par notre logisticien. <\/p><p>Dans ce cas uniquement, nous pourrons intervenir pour l'annuler si vous nous envoyez un mail très rapidement à <a href=\"mailto:hello@we-pop-it.co\" title=\"mailto:hello@we-pop-it.co\"><strong>hello@we-pop-it.co <\/strong><\/a>! Mais ce n'est pas garanti.<\/p>"
          }
        },
        "9f2ce022-2364-4b40-90a7-20580dcd3a76": {
          "type": "category_2",
          "settings": {
            "question": "Je viens de recevoir ma commande et il manque un produit ou un produit est arrivé cassé ou défectueux. Que faire ?",
            "answer": "<p>À réception, pensez toujours à <strong>regarder si votre colis a été endommagé ou partiellement ouvert<\/strong> avant de l'ouvrir complètement. <\/p><p>Si il est endommagé, prenez des <strong>photos de l'état général du colis<\/strong>, des produits cassés et de l'étiquette d'expédition collée sur le colis. Ensuite, envoyez-nous le tout à <a href=\"mailto:hello@we-pop-it.co\" title=\"mailto:hello@we-pop-it.co\"><strong>hello@we-pop-it.co<\/strong><\/a> et nous vous renverrons les <strong>produits manquants ou endommagés<\/strong> !<\/p>"
          }
        },
        "5444bf21-b36c-4e90-b90b-b0342eba52bc": {
          "type": "category_3",
          "settings": {
            "question": "Quels sont les moyens de paiement acceptés par Pop it ?",
            "answer": "<p>Nous acceptons les paiements par <strong>carte bancaire, AMEX, PayPal et Apple Pay<\/strong>. Les paiements par chèque ne sont pas acceptés.<\/p>"
          }
        },
        "39e8455c-fad6-47b4-a8f9-ba0fa489fda1": {
          "type": "category_3",
          "settings": {
            "question": "Comment garantissez-vous un paiement sécurisé sur votre site ?",
            "answer": "<p>Tous les paiements par carte bancaire sont <strong>100% sécurisés par la plateforme Mollie<\/strong>, conformément aux dispositifs de sécurité interbancaires français et internationaux. Mollie est une <strong>infrastructure de paiement web sécurisée<\/strong> (certifiée PCI niveau 1, le niveau de sécurité le plus élevé) et très efficace.<\/p>"
          }
        },
        "c2950670-f3e8-427b-805c-0ff7055ae5ea": {
          "type": "category_3",
          "settings": {
            "question": "Pourquoi le paiement de ma commande a-t-il échoué ?",
            "answer": "<p>Avant tout, pensez à <strong>vérifier la date de validité<\/strong> de votre carte. Si c’est une nouvelle carte, vous devez avoir effectué au préalable un retrait d’argent ou un paiement avec votre carte bancaire (hors internet). <\/p><p>Après plusieurs tentatives, et\/ou plusieurs cartes, <strong>essayez avec une nouvelle adresse e-mail, ou testez un autre moyen de paiement disponible<\/strong> (ex : Paypal). Si votre panier est élevé, pensez à <strong>vérifier le plafond<\/strong> de votre carte bancaire.<\/p>"
          }
        },
        "6ebbe525-0c4a-4ba7-bc23-b91297527a06": {
          "type": "category_3",
          "settings": {
            "question": "Comment utiliser mon code promo ? Peut-on en combiner plusieurs ?",
            "answer": "<p>Une fois votre panier prêt, à l'étape de renseignement de l'adresse de livraison, vous <strong>verrez à droite un champ<\/strong> pour renseigner et appliquer votre code promo. Attention : vous ne pouvez <strong>bénéficier que d'un seul code<\/strong> de réduction par commande.<\/p>"
          }
        },
        "1287910e-8b37-4b12-bf1d-c3a530008f32": {
          "type": "category_3",
          "settings": {
            "question": "J'ai besoin d'une facture, où la trouver ?",
            "answer": "<p>Votre facture est envoyée avec <strong>votre mail de confirmation de commande<\/strong>. N'hésitez pas à nous envoyer un mail à <a href=\"mailto:hello@we-pop-it.co\" title=\"mailto:hello@we-pop-it.co\"><strong>hello@we-pop-it.co<\/strong><\/a> si vous avez du mal à la trouver. Nous vous l'enverrons par mail !<\/p>"
          }
        },
        "2ed14995-7c89-4112-a3ee-61edf1666bf4": {
          "type": "category_4",
          "settings": {
            "question": "Où sont fabriqués vos produits ?",
            "answer": "<p>Tous nos produits sont <strong>fabriqués en France et conçus sous le soleil de Nice<\/strong>, pour vous garantir la meilleure qualité. <\/p>"
          }
        },
        "057577c2-e2b3-4187-bac1-dc3f71435120": {
          "type": "category_4",
          "settings": {
            "question": "Vos formules contiennent-elles des OGM ?",
            "answer": "<p>On ne vous a pas dit que l'on <strong>souhaite uniquement le meilleur<\/strong> pour vous et ceux que vous aimez ? <\/p><p>C'est pour cette raison que nos formules garantissent un maximum d'efficacité <strong>sans jamais contenir d'ingrédients génétiquement modifiés.<\/strong><\/p>"
          }
        },
        "e32693d4-7ab1-4c52-95d2-7f1efe53089a": {
          "type": "category_4",
          "settings": {
            "question": "Vos produits contiennent-ils des allergènes comme du lait, du blé ou des noix ?",
            "answer": "<p>Pour s'adapter aux besoins de toute la famille, <strong>nos gummies et gélules ne contiennent pas d'allergènes<\/strong>. <\/p>"
          }
        },
        "9a4d0cee-d2ec-4da6-9662-b59f4ecee103": {
          "type": "category_4",
          "settings": {
            "question": "Vos produits sont-ils sans gluten ?",
            "answer": "<p>Toutes nos formules sont <strong>garanties sans gluten<\/strong> pour répondre aux besoins de chacun. <\/p>"
          }
        },
        "e60abd65-e951-473f-bba9-f016e9918d0c": {
          "type": "category_4",
          "settings": {
            "question": "Tous vos produits sont-ils bien véganes & cruelty free ?",
            "answer": "<p>Le végane et le cruelty free sont une évidence pour Pop it. <\/p><p>Tous nos <strong>gummies sont certifiées EVE VEGAN<\/strong>. Nous veillons à avoir une complète traçabilité et garantissons des <strong>ingrédients qui ne sont pas d'origine animale<\/strong>. <\/p><p>Quant au cruelty free, nous respectons la <strong>Législation Européenne<\/strong>. <strong>Aucun test n'est réalisé sur des animaux<\/strong> pour nos produits finis comme pour les ingrédients qui les composent.<\/p>"
          }
        },
        "a26f6b94-4fe5-4ffb-a1e8-e85f4bd0254b": {
          "type": "category_4",
          "settings": {
            "question": "Quelle est la meilleure façon de conserver mes gélules et gummies Pop it ?",
            "answer": "<p>Pour garantir un produit avec tous ses bienfaits, il est conseillé de <strong>réaliser la cure dès l'ouverture<\/strong> du pot. Veillez à conserver les produits <strong>à température ambiante et à l'abri de la lumière<\/strong> directe.<\/p>"
          }
        },
        "8a377dd0-496d-453f-8c01-d6dc01fd454f": {
          "type": "category_4",
          "settings": {
            "question": "Comment savoir si mes compléments alimentaires ont expiré ?",
            "answer": "<p>Vous trouverez en-dessous de nos pots <strong>une date d'expiration<\/strong> pour chaque produit. <\/p><p>Elle est indiquée juste à côté du numéro de lot qui garantit une <strong>traçabilité complète de nos produits<\/strong>. Pour votre sécurité, nous vous invitons à <strong>consommer vos compléments avant cette date d’expiration<\/strong>.<\/p>"
          }
        },
        "fde70513-013e-4d15-a4e9-f9c00cfe3234": {
          "type": "category_4",
          "settings": {
            "question": "Combien de temps durent vos produits ?",
            "answer": "<p>Tout dépend de la cure réalisée !<\/p><p>Certaines formules vous permettront une <strong>utilisation d'1 mois, d'autres jusqu'à 3 mois<\/strong>. Retenez qu'une cure de Magnésium durera 60 jours tandis que la formule Biotine vous assurera une peau et des cheveux éclatants pendant 120 jours. Vous pourrez <strong>retrouver nos conseils d'utilisation sur chaque produit<\/strong>.<\/p>"
          }
        },
        "591bb5f7-2149-4c44-86f9-e7cb77f1f648": {
          "type": "category_4",
          "settings": {
            "question": "Les compléments Pop it conviennent-ils aux enfants ?",
            "answer": "<p>Parce que petits et grands ont des besoins bien spécifiques, Pop it a lancé <strong>une gamme KIDS pour vous permettre de prendre soin d'eux avec des formules adaptées<\/strong>. Pour le reste de nos formules, certaines ne conviennent pas aux enfants ! Sur chacun de nos produits, vous retrouverez des <strong>informations précises à ce sujet avec des dosages à adapter<\/strong> selon leurs âges.<\/p>"
          }
        },
        "561859f6-fd33-48f6-a6de-531779844cd9": {
          "type": "category_4",
          "settings": {
            "question": "Vos pots sont-ils en plastique recyclable ?",
            "answer": "<p>Nos compléments alimentaires sont conditionnés dans des <strong>pots en plastique 100% recyclables<\/strong> (pot + bouchon + opercule). <\/p>"
          }
        },
        "946e0205-f026-42e5-b150-301e23b6d83b": {
          "type": "category_4",
          "settings": {
            "question": "Pourquoi avoir fait le choix de format gummies pour certaines de vos formules ?",
            "answer": "<p>Le gummy est un complément alimentaire <strong>fortement dosé<\/strong> en plantes, vitamines ou minéraux avec une galénique particulière.<\/p><p>Ludique et au délicieux goût fruité, il est irrésistible et <strong>100% végane chez Pop it grâce à la pectine de fruit<\/strong> ! Les gommes à mâcher permettant une absorption sublinguale, les <strong>actifs vont être absorbés à travers les petites veines présentes sous la langue<\/strong>, et vont rejoindre la circulation sanguine. La biodisponibilité des actifs est optimale pour un <strong>maximum d'efficacité<\/strong>. <br\/><\/p><p><br\/>Le gummy, c'est aussi zéro contrainte et <strong>idéal pour celles et ceux qui ne peuvent pas avaler les gélules<\/strong> ou pour qui la prise de compléments alimentaires s'apparente à une corvée. C'est le complément <strong>parfait pour les enfants. Pas besoin d'un verre d'eau<\/strong> pour accompagner votre complément. Sentez-vous libre de prendre vos gummies n'importe où !<\/p>"
          }
        },
        "ac87fcc3-64d0-40d1-8e5b-ad538a39b35b": {
          "type": "category_4",
          "settings": {
            "question": "Vos pots ont-ils une sécurité enfant ?",
            "answer": "<p>L'aspect \"bonbon\" pouvant attirer les plus jeunes, nos pots pour les <strong>gummies sont tous dotés d'une sécurité enfant<\/strong>.<\/p>"
          }
        },
        "6b1728ad-72d0-4005-9304-7b182f6386fe": {
          "type": "category_4",
          "settings": {
            "question": "Comment utiliser vos produits ?",
            "answer": "<p>Vous trouverez les <strong>conseils d'utilisation détaillés<\/strong> pour chacun de nos produits, <strong>sur l'étiquette et sur notre site Internet. <\/strong><\/p><p>Contactez notre équipe par email à <a href=\"mailto:hello@we-pop-it.co\" title=\"mailto:hello@we-pop-it.co\"><strong>hello@we-pop-it.co<\/strong><\/a>, sur le chat du site ou via notre formulaire de contact si vous avez des questions ou besoin de conseils personnalisés. <\/p><p><strong>Nous revenons vers vous sous 24h maximum<\/strong> (hors weekends et jours fériés) avec une routine adaptée à vos besoins !<\/p>"
          }
        },
        "cc5d6ada-6f6f-4890-8e0d-d0ad28951347": {
          "type": "category_4",
          "settings": {
            "question": "Où trouver vos produits ?",
            "answer": "<p>Nos produits sont vendus sur <strong>notre site web et sur Amazon<\/strong> en Europe !<\/p>"
          }
        },
        "0bd4fabf-b44f-4129-a014-788739e9841f": {
          "type": "category_5",
          "settings": {
            "question": "Comment créer un compte ?",
            "answer": "<p><strong>Cliquez-ici<\/strong> pour créer un compte client et renseignez votre adresse mail et mot de passe.<\/p>"
          }
        },
        "7e07e48c-33ce-4141-b25d-bd70e8b4001c": {
          "type": "category_5",
          "settings": {
            "question": "Pourquoi créer un compte ?",
            "answer": "<p>Créer un compte vous permet d'avoir <strong>accès à tout l'historique de vos commandes<\/strong> et d'enregistrer vos adresses de livraison et de facturation !<\/p>"
          }
        },
        "0c490cce-887a-4e32-a7da-41f06e6c119b": {
          "type": "category_5",
          "settings": {
            "question": "J'ai perdu mon mot de passe, comment le réinitialiser ?",
            "answer": "<p>Cela arrive à tout le monde ! <\/p><p>Vous pouvez à tout moment réinitialiser votre mot de passe en <strong>cliquant sur \"mot de passe oublié\"<\/strong>. Vous pourrez alors indiquer votre adresse mail et <strong>un mail vous sera envoyé<\/strong> pour créer un nouveau mot de passe.<\/p>"
          }
        },
        "30c4cf42-b674-4506-8a8b-919e29d466e8": {
          "type": "category_5",
          "settings": {
            "question": "Comment puis-je me déconnecter de mon compte ?",
            "answer": "<p>Rien de plus simple, il suffit de vous rendre sur la page <strong>Mon Compte et de cliquer sur le petit bouton<\/strong> en haut à gauche \"<strong>Déconnexion<\/strong>\".<\/p>"
          }
        },
        "dd77089a-8084-46ad-8466-a81d002a52ca": {
          "type": "category_5",
          "settings": {
            "question": "Comment supprimer mon compte client ?",
            "answer": "<p>Vous pouvez joindre Adélaïde de notre équipe en écrivant à <a href=\"mailto:hello@we-pop-it.co\" title=\"mailto:hello@we-pop-it.co\"><strong>hello@we-pop-it.co<\/strong><\/a> pour demander la suppression de votre compte client.<\/p>"
          }
        },
        "6e082f44-e152-4696-b588-1316ba9ef281": {
          "type": "category_5",
          "settings": {
            "question": "Comment supprimer toutes mes données personnelles ?",
            "answer": "<p>Vous pouvez joindre Adélaïde de notre équipe en écrivant à <a href=\"mailto:hello@we-pop-it.co\" title=\"mailto:hello@we-pop-it.co\"><strong>hello@we-pop-it.co<\/strong><\/a> pour demander la suppression de l'ensemble de vos données. N'hésitez pas aussi à <strong>consulter notre Politique de Confidentialité<\/strong>.<\/p>"
          }
        }
      },
      "block_order": [
        "8f4acfdf-e277-4906-9849-918d43148b2a",
        "e534d746-64ae-4407-9460-81be9cc69904",
        "8474b469-f201-4a4f-afff-6df338d8a35e",
        "25172bc4-ca1f-451f-bca2-ac945fa6ecb2",
        "3714bd05-89fb-48f4-967a-db43635b8981",
        "ebe4ec3f-1534-4538-a707-239aba6a2d8b",
        "65687ccb-ea2b-4465-8ec4-b88b11b7c933",
        "1b714378-dfb3-41a0-9f69-6680410b2b28",
        "2174bf0a-c056-43eb-b32f-1fa32235d0ac",
        "9f2ce022-2364-4b40-90a7-20580dcd3a76",
        "5444bf21-b36c-4e90-b90b-b0342eba52bc",
        "39e8455c-fad6-47b4-a8f9-ba0fa489fda1",
        "c2950670-f3e8-427b-805c-0ff7055ae5ea",
        "6ebbe525-0c4a-4ba7-bc23-b91297527a06",
        "1287910e-8b37-4b12-bf1d-c3a530008f32",
        "2ed14995-7c89-4112-a3ee-61edf1666bf4",
        "057577c2-e2b3-4187-bac1-dc3f71435120",
        "e32693d4-7ab1-4c52-95d2-7f1efe53089a",
        "9a4d0cee-d2ec-4da6-9662-b59f4ecee103",
        "e60abd65-e951-473f-bba9-f016e9918d0c",
        "a26f6b94-4fe5-4ffb-a1e8-e85f4bd0254b",
        "8a377dd0-496d-453f-8c01-d6dc01fd454f",
        "fde70513-013e-4d15-a4e9-f9c00cfe3234",
        "591bb5f7-2149-4c44-86f9-e7cb77f1f648",
        "561859f6-fd33-48f6-a6de-531779844cd9",
        "946e0205-f026-42e5-b150-301e23b6d83b",
        "ac87fcc3-64d0-40d1-8e5b-ad538a39b35b",
        "6b1728ad-72d0-4005-9304-7b182f6386fe",
        "cc5d6ada-6f6f-4890-8e0d-d0ad28951347",
        "0bd4fabf-b44f-4129-a014-788739e9841f",
        "7e07e48c-33ce-4141-b25d-bd70e8b4001c",
        "0c490cce-887a-4e32-a7da-41f06e6c119b",
        "30c4cf42-b674-4506-8a8b-919e29d466e8",
        "dd77089a-8084-46ad-8466-a81d002a52ca",
        "6e082f44-e152-4696-b588-1316ba9ef281"
      ],
      "settings": {
        "title": "FOIRE AUX QUESTIONS",
        "header_text": "<p>Une question, un doute ? <br\/>Nous répondons à toutes vos questions.<\/p>",
        "category1_title": "Livraison & Retours",
        "category2_title": "Commande",
        "category3_title": "Paiement & Facturation",
        "category4_title": "Produits & Utilisation",
        "category5_title": "Compte client",
        "category6_title": "",
        "title_accordion_color": "#4b9b7d",
        "content_accordion_color": "#201a1c"
      }
    }
  },
  "order": [
    "main-faq"
  ]
}
